fmridenoise/__init__.py
fmridenoise/__main__.py
fmridenoise/_version.py
fmridenoise/interfaces/__init__.py
fmridenoise/interfaces/bids.py
fmridenoise/interfaces/confounds.py
fmridenoise/interfaces/connectivity.py
fmridenoise/interfaces/denoising.py
fmridenoise/interfaces/pipeline_selector.py
fmridenoise/interfaces/quality_measures.py
fmridenoise/interfaces/report_creator.py
fmridenoise/interfaces/smoothing.py
fmridenoise/interfaces/utility.py
fmridenoise/parcellation/__init__.py
fmridenoise/parcellation/atlas-Schaefer2018_desc-200Parcels7Networks_dseg_desc-distance-matrix.npy
fmridenoise/parcellation/tpl-MNI152NLin2009cAsym_res-01_atlas-Schaefer2018_desc-200Parcels7Networks_dseg.nii.gz
fmridenoise/parcellation/tpl-MNI152NLin6Asym_res-01_atlas-Schaefer2018_desc-200Parcels7Networks_dseg.nii.gz
fmridenoise/pipelines/__init__.py
fmridenoise/pipelines/pipeline-24HMP_8Phys_SpikeReg.json
fmridenoise/pipelines/pipeline-24HMP_8Phys_SpikeReg_4GS.json
fmridenoise/pipelines/pipeline-24HMP_aCompCor_SpikeReg.json
fmridenoise/pipelines/pipeline-24HMP_aCompCor_SpikeReg_4GS.json
fmridenoise/pipelines/pipeline-ICA-AROMA_8Phys.json
fmridenoise/pipelines/pipeline-ICA-AROMA_8Phys_4GS.json
fmridenoise/pipelines/pipeline-Null.json
fmridenoise/scripts/fmridenoise
fmridenoise/utils/__init__.py
fmridenoise/utils/dataset_description_template.json
fmridenoise/utils/entities.py
fmridenoise/utils/error_data.py
fmridenoise/utils/json_validator.py
fmridenoise/utils/numeric.py
fmridenoise/utils/plotting.py
fmridenoise/utils/profiling.py
fmridenoise/utils/report_creator.py
fmridenoise/utils/temps.py
fmridenoise/utils/traits.py
fmridenoise/utils/utils.py
fmridenoise/utils/dataclasses/__init__.py
fmridenoise/utils/dataclasses/excluded_subjects.py
fmridenoise/utils/dataclasses/runtime_info.py
fmridenoise/utils/report_templates/pipeline_table.j2
fmridenoise/utils/report_templates/report_base.j2
fmridenoise/utils/report_templates/report_style.css
fmridenoise/utils/report_templates/svg_definitions.j2
fmridenoise-0.2.1.dist-info/LICENSE
fmridenoise-0.2.1.dist-info/METADATA
fmridenoise-0.2.1.dist-info/WHEEL
fmridenoise-0.2.1.dist-info/top_level.txt
fmridenoise-0.2.1.dist-info/RECORD
