Metadata-Version: 2.1
Name: fmridenoise
Version: 0.2.1
Summary: fMRIDenoise - automated denoising, denoising strategies comparison, and functional connectivity data quality control.
Home-page: https://github.com/nbraingroup/fmridenoise
Author: Karolina Finc, Mateusz Chojnowski, Kamil Bonna
Author-email: karolinafinc@gmail.com, mateus.chojnowski@gmail.com, kongokou@gmail.com
License: License :: OSI Approved :: Apache Software License
Platform: UNKNOWN
Classifier: Development Status :: 4 - Beta
Classifier: Environment :: Console
Classifier: Intended Audience :: Science/Research
Classifier: Programming Language :: Python :: 3.7
Requires-Dist: nibabel
Requires-Dist: matplotlib
Requires-Dist: seaborn
Requires-Dist: numpy
Requires-Dist: scipy
Requires-Dist: nilearn
Requires-Dist: pandas
Requires-Dist: jsonschema
Requires-Dist: traits
Requires-Dist: nipype
Requires-Dist: sklearn
Requires-Dist: pydot
Requires-Dist: pybids
Requires-Dist: psutil
Requires-Dist: jinja2
Requires-Dist: frozendict
